sferriol/zarr/__init__.py
sferriol/zarr/fsspec_.py
sferriol_zarr-0.4.0.dist-info/licenses/LICENSE
sferriol_zarr-0.4.0.dist-info/METADATA
sferriol_zarr-0.4.0.dist-info/WHEEL
sferriol_zarr-0.4.0.dist-info/top_level.txt
sferriol_zarr-0.4.0.dist-info/RECORD
