Metadata-Version: 2.4
Name: sferriol-zarr
Version: 0.4.0
Summary: Read only Zarr storage
Home-page: https://gitlab.in2p3.fr/sferriol/sferriol-zarr
Author: Sylvain Ferriol
Author-email: s.ferriol@ipnl.in2p3.fr
Classifier: License :: OSI Approved :: The Unlicense (Unlicense)
Classifier: Operating System :: OS Independent
Classifier: Programming Language :: Python :: 3
Requires-Python: >=3.5
License-File: LICENSE
Requires-Dist: zarr<3,>=2.11.0
Requires-Dist: fsspec>=2025.3.0
Requires-Dist: fsspec_xrootd>=0.5.1
Dynamic: license-file
